[
  {
    "MFY": "31",
    "end": "9",
    "start": "8"
  },
  {
    "MFY": "133",
    "end": "10",
    "start": "9"
  },
  {
    "MFY": "27",
    "end": "11",
    "start": "10"
  },
  {
    "MFY": "29",
    "end": "12",
    "start": "11"
  },
  {
    "MFY": "49",
    "end": "13",
    "start": "12"
  },
  {
    "MFY": "111",
    "end": "14",
    "start": "13"
  },
  {
    "MFY": "25",
    "end": "15",
    "start": "14"
  },
  {
    "MFY": "14",
    "end": "16",
    "start": "15"
  },
  {
    "MFY": "23",
    "end": "17",
    "start": "16"
  },
  {
    "MFY": "44",
    "end": "18",
    "start": "17"
  }
]